arnelify-server-ffi.cpython-311-x86_64-linux-gnu.so
arnelify_server/__init__.py
arnelify_server/index.py
arnelify_server/contracts/__init__.py
arnelify_server/contracts/res.py
arnelify_server-0.7.8.dist-info/LICENSE
arnelify_server-0.7.8.dist-info/METADATA
arnelify_server-0.7.8.dist-info/WHEEL
arnelify_server-0.7.8.dist-info/top_level.txt
arnelify_server-0.7.8.dist-info/RECORD
