Metadata-Version: 2.1
Name: arnelify-server
Version: 0.7.8
Summary: Minimalistic dynamic library which is a powerful server written in C and C++.
Home-page: https://github.com/arnelify/arnelify-server-python
Author: Arnelify
License: MIT
Keywords: arnelify arnelify-server-python arnelify-server
Classifier: Programming Language :: Python :: 3
License-File: LICENSE
Requires-Dist: cffi
Requires-Dist: setuptools
Requires-Dist: wheel
